{
    "version": "0.2",
    "ignorePaths": [],
    "dictionaryDefinitions": [],
    "dictionaries": [],
    "words": [
        "Aguasnegras",
        "alteraci",
        "Alteracianos",
        "Alteracino",
        "Altonato",
        "amani",
        "Amani",
        "ankoan",
        "Ankoan",
        "annihilan",
        "Annihilan",
        "Annihilanos",
        "aqir",
        "Aqir",
        "aracnatidós",
        "Aracnatidós",
        "arakkoa",
        "Arakkoa",
        "arathor",
        "arathorian",
        "Azeroth",
        "azerothian",
        "Baradianos",
        "baradin",
        "Barbabronce",
        "Barbabronces",
        "baronny",
        "blackrock",
        "blackwater",
        "Blackwater",
        "Blackwaters",
        "bonechewer",
        "bronzebeard",
        "Cazatormentas",
        "chieftess",
        "chimachi",
        "Chimachi",
        "chitera",
        "Chitera",
        "coildom",
        "commandery",
        "daihoshu",
        "Daihoshu",
        "dalaranian",
        "Dalaranianos",
        "darkiron",
        "Darnassiano",
        "Dracohalcón",
        "draenei",
        "Draenei",
        "dragonking",
        "dragonmaw",
        "dragonqueen",
        "drakkari",
        "Drakkari",
        "drogbar",
        "Drogbar",
        "Drogbars",
        "drottinn",
        "Drottinn",
        "drust",
        "Drust",
        "durotaric",
        "Durotario",
        "Durotarios",
        "dwarven",
        "Dwarven",
        "Elfico",
        "Elven",
        "Enánico",
        "Ered'ruin",
        "eredar",
        "Eredar",
        "eredruin",
        "Faraona",
        "farraki",
        "Farraki",
        "Faucedracos",
        "Fjorthir",
        "fria",
        "frostborn",
        "Frostborn",
        "frostnymph",
        "frostwolf",
        "frue",
        "Frue",
        "furbolg",
        "Furbolg",
        "Furbolgs",
        "gilblin",
        "Gilblin",
        "Gilblins",
        "gilnean",
        "Gilneaneanos",
        "Gilneano",
        "gnoll",
        "Gnoll",
        "Gnolls",
        "gorloc",
        "Gorloc",
        "Gorlocs",
        "Grumél",
        "Gruméls",
        "grummle",
        "Grummle",
        "Grummles",
        "gurubashi",
        "Gurubashi",
        "hatya",
        "Hatya",
        "heqa",
        "Heqa",
        "highborne",
        "Highbornes",
        "highelf",
        "highmountain",
        "Highmountains",
        "Higmountain",
        "hillsbrad",
        "Hillsbradian",
        "Hillsbradians",
        "hossu",
        "Hossu",
        "hout",
        "Hout",
        "hozen",
        "Hozen",
        "hyldnir",
        "Hyldnir",
        "Infrareina",
        "Infrarey",
        "Iskronir",
        "Jabaespín",
        "Jabaespínes",
        "jarldom",
        "jinyu",
        "Jinyu",
        "joshu",
        "Joshu",
        "juji",
        "Juji",
        "kalimdor",
        "khagan",
        "Khagan",
        "khaganat",
        "Khaganat",
        "khanat",
        "Khanat",
        "Kohi",
        "koku",
        "Koku",
        "kokujin",
        "Kokujin",
        "kokuo",
        "Kokuo",
        "kori",
        "Kori",
        "Kul'tiran",
        "kvaldir",
        "Kvaldir",
        "kyodan",
        "Kyodan",
        "kyowa",
        "Kyowa",
        "Kyparita",
        "kyparite",
        "legionlord",
        "lordaeronian",
        "Lordaeroniano",
        "Lordaeronianos",
        "machi",
        "Machi",
        "mada",
        "Mag'har",
        "maghar",
        "magnataur",
        "Magnataur",
        "Magnatauro",
        "Magnatauros",
        "Magnataurs",
        "Mantide",
        "Mantides",
        "Mascahueso",
        "Mascahuesos",
        "mechagnome",
        "Mechagnomo",
        "Mechagnomos",
        "moarg",
        "mogu",
        "Mogu",
        "Mogus",
        "Mok'nathal",
        "moknathal",
        "murloc",
        "Murloc",
        "Murlocs",
        "naga",
        "Nagas",
        "Nalak",
        "Nalak'sha",
        "Nalakites",
        "nathrezim",
        "Nathrezim",
        "Natoescarcha",
        "Natoescarchas",
        "Nazja",
        "Nazmani",
        "nerubian",
        "Nerubian",
        "Nerubiano",
        "Nerubianos",
        "Nerubians",
        "nightborne",
        "Nightborne",
        "Nightbornes",
        "niout",
        "Niout",
        "Nocheterna",
        "Nomarca",
        "nome",
        "northsea",
        "Northsea",
        "Northseans",
        "nraqi",
        "odoshiyori",
        "Odoshiyori",
        "omachi",
        "Omachi",
        "otera",
        "Otera",
        "overlady",
        "overthane",
        "Pandarens",
        "qiraj",
        "qiraji",
        "Qiraji",
        "Quel'dorei",
        "quilboar",
        "Quilboar",
        "Quilboars",
        "Riecráneo",
        "Riecráneos",
        "saito",
        "Saito",
        "saurok",
        "Saurok",
        "Sauroks",
        "sayaadi",
        "sethrak",
        "Sethrak",
        "shadowmoon",
        "Shath'yar",
        "shathyar",
        "Sheili",
        "Shen",
        "shiro",
        "Shiro",
        "shivarra",
        "Shivarran",
        "Shivarras",
        "shushoo",
        "Shushoo",
        "Sin'dorei",
        "snobold",
        "Snobold",
        "Snóbold",
        "Snobolds",
        "Snóbolds",
        "sojo",
        "Sojo",
        "sokan",
        "Sokan",
        "Solsticeanos",
        "Solsticiano",
        "Sombraluna",
        "spanish",
        "Staroveric",
        "stormheimir",
        "Stormheimir",
        "stormreaver",
        "Stromgardianoss",
        "Stromic",
        "Súcubo",
        "Súcubos",
        "taishou",
        "Taishou",
        "taunka",
        "Taunka",
        "tauren",
        "Taurens",
        "tera",
        "Tera",
        "Terraneo",
        "Terraneos",
        "theramore",
        "Theramoreano",
        "Theramoreanos",
        "thunderlord",
        "Thunderlord",
        "tidemistress",
        "tirassian",
        "titanforged",
        "Titanforged",
        "titulos",
        "Tol'vir",
        "tolvir",
        "tortollan",
        "Tortollan",
        "Tortollans",
        "toshiyori",
        "Toshiyori",
        "trogg",
        "Trogg",
        "Troggs",
        "tuskarr",
        "Tuskarr",
        "underking",
        "underqueen",
        "Vagayermos",
        "vicomtesse",
        "vrykul",
        "Vrykul",
        "vulpera",
        "Vulpera",
        "warlady",
        "warmother",
        "warsong",
        "wastewander",
        "wildhammer",
        "Wildhammer",
        "wolvar",
        "Wolvar",
        "yaungol",
        "Yaungol",
        "zandalari",
        "Zandalari",
        "Zarato",
        "Zarisa",
        "zhang",
        "Zhang"
    ],
    "ignoreWords": [],
    "import": []
}
